{"examples_html_index.md":"0694487b","examples_javascript_index.md":"5cedeb80","examples_jquery_index.md":"a11dc690","examples_vue_index.md":"5fdf0935","index.md":"8f25c373","note_nodejs_index.md":"62d9f211","note_nodejs_websocket.md":"b060621a","note_实用工具_index.md":"c105c2d5","note_实用工具_mock.md":"c0fe5b33","project_index.md":"4906b418","project_mobile_newbee_index.md":"bca54b83","project_mobile_前端铺子_index.md":"bd929fdb","project_mobile_小情书_index.md":"e9ccab92","project_mobile_约拍_index.md":"c01bd891","project_mobile_萤火商城_index.md":"c47142b9","project_mobile_饿了吗_index.md":"129ed1d3","project_pc_网易云音乐_index.md":"2cbd6bb2"}
